experimentlogger/ExperimentLogger.py
experimentlogger/__init__.py
experimentlogger/tests/__init__.py
experimentlogger/tests/testFileLogger.py
experimentlogger/utils/__init__.py
experimentlogger/utils/errors.py
experimentlogger_jathr-0.0.5.dist-info/METADATA
experimentlogger_jathr-0.0.5.dist-info/WHEEL
experimentlogger_jathr-0.0.5.dist-info/top_level.txt
experimentlogger_jathr-0.0.5.dist-info/RECORD
